mcp_server_file_finder/__init__.py
mcp_server_file_finder/__main__.py
mcp_server_file_finder/everything_sdk.py
mcp_server_file_finder/platform_search.py
mcp_server_file_finder/search_interface.py
mcp_server_file_finder/server.py
mcp_server_file_finder-0.2.1.dist-info/METADATA
mcp_server_file_finder-0.2.1.dist-info/WHEEL
mcp_server_file_finder-0.2.1.dist-info/entry_points.txt
mcp_server_file_finder-0.2.1.dist-info/licenses/LICENSE
mcp_server_file_finder-0.2.1.dist-info/RECORD
